[
  { "name": "CT ZWA10", "gen": "1ST", "years": "2011–2022" },
  { "name": "ES V20", "gen": "1ST", "years": "1989–1991" },
  { "name": "ES XV10", "gen": "2ND", "years": "1991–1996" },
  { "name": "ES XV20", "gen": "3RD", "years": "1996–2001" },
  { "name": "ES XV30", "gen": "4TH", "years": "2001–2006" },
  { "name": "ES XV40", "gen": "5TH", "years": "2006–2012" },
  { "name": "ES XV60", "gen": "6TH", "years": "2012–2018" },
  { "name": "ES XZ10", "gen": "7TH", "years": "2018–2026" },
  { "name": "GS S140", "gen": "1ST", "years": "1993–1997" },
  { "name": "GS S160", "gen": "2ND", "years": "1997–2005" },
  { "name": "GS S190", "gen": "3RD", "years": "2005–2011" },
  { "name": "GS L10", "gen": "4TH", "years": "2012–2020" },
  { "name": "GX J120", "gen": "1ST", "years": "2002–2009" },
  { "name": "GX J150", "gen": "2ND", "years": "2009–2023" },
  { "name": "GX J250", "gen": "3RD", "years": "2024–2026" },
  { "name": "HS ANF10", "gen": "1ST", "years": "2009–2018" },
  { "name": "IS XE10", "gen": "1ST", "years": "1999–2005" },
  { "name": "IS XE20", "gen": "2ND", "years": "2005–2013" },
  { "name": "IS XE30", "gen": "3RD", "years": "2013–2026" },
  { "name": "LBX AY10", "gen": "1ST", "years": "2023–2026" },
  { "name": "LC Z100", "gen": "1ST", "years": "2017–2026" },
  { "name": "LFA L10", "gen": "1ST", "years": "2010–2012" },
  { "name": "LM AH30", "gen": "1ST", "years": "2019–2023" },
  { "name": "LM AW40", "gen": "2ND", "years": "2023–2026" },
  { "name": "LS XF10", "gen": "1ST", "years": "1989–1994" },
  { "name": "LS XF20", "gen": "2ND", "years": "1994–2000" },
  { "name": "LS XF30", "gen": "3RD", "years": "2000–2006" },
  { "name": "LS XF40", "gen": "4TH", "years": "2006–2017" },
  { "name": "LS XF50", "gen": "5TH", "years": "2017–2026" },
  { "name": "LX J80", "gen": "1ST", "years": "1995–1997" },
  { "name": "LX J100", "gen": "2ND", "years": "1998–2007" },
  { "name": "LX J200", "gen": "3RD", "years": "2007–2021" },
  { "name": "LX J310", "gen": "4TH", "years": "2021–2026" },
  { "name": "NX AZ10", "gen": "1ST", "years": "2014–2021" },
  { "name": "NX AZ20", "gen": "2ND", "years": "2021–2026" },
  { "name": "RC C10", "gen": "1ST", "years": "2014–2026" },
  { "name": "RX XU10", "gen": "1ST", "years": "1998–2003" },
  { "name": "RX XU30", "gen": "2ND", "years": "2003–2009" },
  { "name": "RX AL10", "gen": "3RD", "years": "2008–2015" },
  { "name": "RX AL20", "gen": "4TH", "years": "2015–2022" },
  { "name": "RX ALA10", "gen": "5TH", "years": "2022–2026" },
  { "name": "RZ EB10", "gen": "1ST", "years": "2022–2026" },
  { "name": "SC Z30", "gen": "1ST", "years": "1991–2000" },
  { "name": "SC Z40", "gen": "2ND", "years": "2001–2010" },
  { "name": "TX T10", "gen": "1ST", "years": "2023–2026" },
  { "name": "UX ZA10", "gen": "1ST", "years": "2018–2026" }
]